jupyterlab_snippets/__init__.py
jupyterlab_snippets/_version.py
jupyterlab_snippets/handlers.py
jupyterlab_snippets/loader.py
jupyterlab_snippets/labextension/package.json
jupyterlab_snippets/labextension/static/110.e0a0b2660a791af31658.js
jupyterlab_snippets/labextension/static/534.c626d78413d9f38c2a41.js
jupyterlab_snippets/labextension/static/remoteEntry.271be5d1024c914c8203.js
jupyterlab_snippets/labextension/static/style.js
jupyterlab_snippets/labextension/static/third-party-licenses.json
jupyterlab_snippets-0.4.1.data/data/etc/jupyter/jupyter_notebook_config.d/jupyterlab_snippets.json
jupyterlab_snippets-0.4.1.data/data/etc/jupyter/jupyter_server_config.d/jupyterlab_snippets.json
jupyterlab_snippets-0.4.1.data/data/share/jupyter/labextensions/jupyterlab-snippets/install.json
jupyterlab_snippets-0.4.1.data/data/share/jupyter/labextensions/jupyterlab-snippets/package.json
jupyterlab_snippets-0.4.1.data/data/share/jupyter/labextensions/jupyterlab-snippets/static/110.e0a0b2660a791af31658.js
jupyterlab_snippets-0.4.1.data/data/share/jupyter/labextensions/jupyterlab-snippets/static/534.c626d78413d9f38c2a41.js
jupyterlab_snippets-0.4.1.data/data/share/jupyter/labextensions/jupyterlab-snippets/static/remoteEntry.271be5d1024c914c8203.js
jupyterlab_snippets-0.4.1.data/data/share/jupyter/labextensions/jupyterlab-snippets/static/style.js
jupyterlab_snippets-0.4.1.data/data/share/jupyter/labextensions/jupyterlab-snippets/static/third-party-licenses.json
jupyterlab_snippets-0.4.1.dist-info/LICENSE
jupyterlab_snippets-0.4.1.dist-info/METADATA
jupyterlab_snippets-0.4.1.dist-info/WHEEL
jupyterlab_snippets-0.4.1.dist-info/top_level.txt
jupyterlab_snippets-0.4.1.dist-info/RECORD
